{
  "parent": "minecraft:recipes/root",
  "criteria": {
    "has_item": {
      "conditions": {
        "items": [
          {
            "items": "transfer_labels:itemstack_insert_transfer_label"
          }
        ]
      },
      "trigger": "minecraft:inventory_changed"
    },
    "has_the_recipe": {
      "conditions": {
        "recipe": "transfer_labels:itemstack_extract_label_to_itemstack_insert_label"
      },
      "trigger": "minecraft:recipe_unlocked"
    }
  },
  "requirements": [
    [
      "has_the_recipe",
      "has_item"
    ]
  ],
  "rewards": {
    "recipes": [
      "transfer_labels:itemstack_extract_label_to_itemstack_insert_label"
    ]
  }
}